pandocacro/__init__.py
pandocacro/keys.py
pandocacro/list.py
pandocacro/options.py
pandocacro/pandocacro.py
pandocacro/translate.py
pandoc_acro-0.10.1.dist-info/LICENSE.rst
pandoc_acro-0.10.1.dist-info/METADATA
pandoc_acro-0.10.1.dist-info/WHEEL
pandoc_acro-0.10.1.dist-info/entry_points.txt
pandoc_acro-0.10.1.dist-info/top_level.txt
pandoc_acro-0.10.1.dist-info/zip-safe
pandoc_acro-0.10.1.dist-info/RECORD
