Metadata-Version: 2.1
Name: pandoc-acro
Version: 0.10.1
Summary: Pandoc filter for managing acronyms
Home-page: https://kprussing.github.io/pandoc-acro/
Author: Keith F. Prussing
Author-email: kprussing74@gmail.com
License: UNKNOWN
Keywords: pandoc,filter,acronyms
Platform: UNKNOWN
Classifier: Development Status :: 4 - Beta
Classifier: Intended Audience :: Other Audience
Classifier: Topic :: Documentation
Classifier: Topic :: Text Processing :: Filters
Classifier: License :: OSI Approved :: BSD License
Classifier: Programming Language :: Python :: 3
Classifier: Programming Language :: Python :: 3.6
Classifier: Programming Language :: Python :: 3.7
Classifier: Programming Language :: Python :: 3.8
Classifier: Programming Language :: Python :: 3.9
Classifier: Programming Language :: Python :: 3 :: Only
Requires-Python: <4,>=3.6
Requires-Dist: panflute (>=2.0)
